README.rst
pyproject.toml
setup.py
./__init__.py
./__main__.py
./nim.py
nim.egg-info/PKG-INFO
nim.egg-info/SOURCES.txt
nim.egg-info/dependency_links.txt
nim.egg-info/entry_points.txt
nim.egg-info/not-zip-safe
nim.egg-info/requires.txt
nim.egg-info/top_level.txt